[
    {
        "post_id":8734,
        "thread_id":8734,
        "title":"[SOLVED]I need some help",
        "user_id":68,
        "username":"totosql",
        "post_date":"2016-10-27 08:10:13",
        "message":"Hello guy what kind of error is this one I got this laptop owner say sometime turn off so I check it  it was  dirty whit dust inside no water damage mark I clean the mobo I upgrade the hard drive put back and run normal for me but after the  send  a pic whit this error any idea i will put more info later when they bring the laptop"
    },
    {
        "post_id":8736,
        "thread_id":8734,
        "title":"[SOLVED]I need some help",
        "user_id":145,
        "username":"Sykulski",
        "post_date":"2016-10-27 08:13:26",
        "message":"Looking like bad ram or ram socket"
    },
    {
        "post_id":8745,
        "thread_id":8734,
        "title":"[SOLVED]I need some help",
        "user_id":2,
        "username":"dukefawks",
        "post_date":"2016-10-27 09:05:47",
        "message":"Try different RAM and if still problem then try 1 slot at a time. RAM slots are not repairable if 1 is bad."
    },
    {
        "post_id":8747,
        "thread_id":8734,
        "title":"[SOLVED]I need some help",
        "user_id":68,
        "username":"totosql",
        "post_date":"2016-10-27 09:40:20",
        "message":"hi duke quit question when the ram slots go bad is physics or logic"
    },
    {
        "post_id":8754,
        "thread_id":8734,
        "title":"[SOLVED]I need some help",
        "user_id":68,
        "username":"totosql",
        "post_date":"2016-10-27 11:11:24",
        "message":"Well I take one memory out upper first and I tap tap around the mobo boom frezze do funy stuff power off take lower memory out and install upper memory tap tap around no drama look ok I a take out memory and install 1 stick 4 gb upper slot no drama work thank you.... this was  a MacBookPro9,2  \"Core i5\" 2.5 13\" Mid-2012"
    }
]