{"post_id":80613,"thread_id":61766,"title":"A1466 no backlight , Image is present","user_id":30233,"username":"manumathew.017","post_date":"2021-09-25 16:27:31","message":"I have 8.5V o\/p, Seems like boosting is not occurring, Changed the driver IC, The feedback is proper (Checked the continuity from D7701 second pin to A5). \nI have 2.8V BKL_EN . I am ....STUCKKKKKKKKKKKKKKKKK........................."}
{"post_id":80617,"thread_id":61766,"title":"A1466 no backlight , Image is present","user_id":682,"username":"2informaticos","post_date":"2021-09-25 16:57:19","message":"If is not secret, can we know what board do you have on the desk???\n\nDid you try known good LCD assembly?\nBKL_PWM level?\nTry 2-3 times PRAM reset, just in case.,"}
{"post_id":80653,"thread_id":61766,"title":"A1466 no backlight , Image is present","user_id":30233,"username":"manumathew.017","post_date":"2021-09-26 14:05:50","message":"I dont have extra lcd for trial, \nBKL_PWM - Its high If I am not wrong it is 2.1V.\nPRAM reset didn't help \nRevealing the secret Board is 820-00165A"}
{"post_id":80657,"thread_id":61766,"title":"A1466 no backlight , Image is present","user_id":682,"username":"2informaticos","post_date":"2021-09-26 19:34:16","message":"Check R7717-22; post diode mode to ground on all them.\nAlso at both pins of D7701.\nPost real BKL_PWM level."}
{"post_id":84582,"thread_id":61766,"title":"A1466 no backlight , Image is present","user_id":30233,"username":"manumathew.017","post_date":"2022-01-05 11:20:09","message":"I have resoldered the backlight chip, Now when I start there is backlight ,,,,\nWhen I reboot no backlight. Once starts then it keeps working. Does it a software issue or I should resolder it again?"}
{"post_id":84583,"thread_id":61766,"title":"A1466 no backlight , Image is present","user_id":682,"username":"2informaticos","post_date":"2022-01-05 11:29:35","message":"Did PRAM reset again?\nYou should be sure to get good solders."}
{"post_id":85331,"thread_id":61766,"title":"A1466 no backlight , Image is present","user_id":30233,"username":"manumathew.017","post_date":"2022-01-20 13:49:09","message":"I have resoldered properly... Now the backlight is working  ..... Only one issue...\n\nThere is 16 different brightness control by pressing the F1 and F2 key (Low to High), Only on the 15th position of brightness does it's flickering. I mean brightness doesn't stay stable. It's slightly flickering."}
{"post_id":85344,"thread_id":61766,"title":"A1466 no backlight , Image is present","user_id":682,"username":"2informaticos","post_date":"2022-01-20 17:57:22","message":"Should try new backlight chip, U7701."}
{"post_id":85507,"thread_id":61766,"title":"A1466 no backlight , Image is present","user_id":30233,"username":"manumathew.017","post_date":"2022-01-24 13:31:34","message":"Seems like back light issue solved...\nNow when I press the power button sometimes it boots, sometimes it doesn't boot or no chime sound just Fan is rotating continues, Tried pram reset and Cleanme... Doesnt help"}
{"post_id":85508,"thread_id":61766,"title":"A1466 no backlight , Image is present","user_id":682,"username":"2informaticos","post_date":"2022-01-24 13:42:44","message":"Didn't note this problem before changing U7701?\nShouldn't be caused by this change however.\n\nCPU core comes high, PLT_RESET_L present?"}
{"post_id":85513,"thread_id":61766,"title":"A1466 no backlight , Image is present","user_id":30233,"username":"manumathew.017","post_date":"2022-01-24 14:44:46","message":"Checked after removing the board PLT_RESET_L is high 3.3V,,,,,"}
{"post_id":85514,"thread_id":61766,"title":"A1466 no backlight , Image is present","user_id":682,"username":"2informaticos","post_date":"2022-01-24 15:03:42","message":"Check for USB activity.\nAlso post CPU core voltage in this case."}
{"post_id":85559,"thread_id":61766,"title":"A1466 no backlight , Image is present","user_id":30233,"username":"manumathew.017","post_date":"2022-01-25 14:42:21","message":"Connected an external SSD ---> Removed the internal SSD ---> System booted properly, But after 3rd restart, it again went to that weird mode (Fan running not booting)----> Measured PPVCC_S0_CPU at weird mode= 1.808V"}
{"post_id":85560,"thread_id":61766,"title":"A1466 no backlight , Image is present","user_id":682,"username":"2informaticos","post_date":"2022-01-25 14:51:34","message":"1.8V is correct voltage.\nDid you check for USB activity???"}
{"post_id":85561,"thread_id":61766,"title":"A1466 no backlight , Image is present","user_id":30233,"username":"manumathew.017","post_date":"2022-01-25 15:18:44","message":"This SATA to USB cable has two LED's they blinks only when its booting , At weird mode they are not blinking but just glowing"}
{"post_id":85580,"thread_id":61766,"title":"A1466 no backlight , Image is present","user_id":30233,"username":"manumathew.017","post_date":"2022-01-26 05:08:02","message":"Did I answer your question? :rolleyes:"}
{"post_id":85587,"thread_id":61766,"title":"A1466 no backlight , Image is present","user_id":682,"username":"2informaticos","post_date":"2022-01-26 08:00:46","message":"Any history fault, liquid sign?\nJust in case, try known good BIOS, clean ME."}
{"post_id":85591,"thread_id":61766,"title":"A1466 no backlight , Image is present","user_id":30233,"username":"manumathew.017","post_date":"2022-01-26 08:15:54","message":"Didn't try known bios, CleanME doesn't help. No Liquid sign..."}
{"post_id":85642,"thread_id":61766,"title":"A1466 no backlight , Image is present","user_id":30233,"username":"manumathew.017","post_date":"2022-01-27 11:05:59","message":"Will, it makes sense re soldering the display connecter ? Does SMC_LID control sleep activity?"}
{"post_id":85653,"thread_id":61766,"title":"A1466 no backlight , Image is present","user_id":682,"username":"2informaticos","post_date":"2022-01-27 18:29:10","message":"SMC_LID puts system to sleep, when lid is closed.\nAn incorrect level can cause weird issue; if fluctuates close to its threshold voltage."}
{"post_id":85704,"thread_id":61766,"title":"A1466 no backlight , Image is present","user_id":30233,"username":"manumathew.017","post_date":"2022-01-29 17:17:35","message":"Changed the connector, seems like that sleep issue solved ..... Just gone through hw diagnostic test .... Got NDT001 - Issue with the thunder bolt Hardware... Never ending problems\ud83d\ude23"}
{"post_id":85705,"thread_id":61766,"title":"A1466 no backlight , Image is present","user_id":682,"username":"2informaticos","post_date":"2022-01-29 17:57:12","message":"You may disable thunderbolt, if nobody needs it."}
{"post_id":85746,"thread_id":61766,"title":"A1466 no backlight , Image is present","user_id":30233,"username":"manumathew.017","post_date":"2022-01-31 10:59:34","message":"Can I know the commands for disabling it please?"}
{"post_id":85760,"thread_id":61766,"title":"A1466 no backlight , Image is present","user_id":682,"username":"2informaticos","post_date":"2022-01-31 13:48:12","message":"If all other functions are good, no need to disable anything.\nIf no thunderbolt\/display port will be used.\nRemoving Q3080, will let thunderbolt \"out of game\"."}
