[
    {
        "post_id":61200,
        "thread_id":59521,
        "title":"820-4924-A .520A not turning on",
        "user_id":24760,
        "username":"2click",
        "post_date":"2020-06-18 23:51:10",
        "message":"I have another macbook pro A1502 board model 820-4924-A that is consuming 520 ma, it does not have USB activity, it does not have thunderbolt activity. I have all the rails present (from the schematic page 68)... this is the second board that I have with this problem, please help me figure it out. \nThe board is in S0 state, has cpu vcore, allsys_pwrgd\nWhat else can I check? Thank you!"
    },
    {
        "post_id":61208,
        "thread_id":59521,
        "title":"820-4924-A .520A not turning on",
        "user_id":682,
        "username":"2informaticos",
        "post_date":"2020-06-19 04:32:02",
        "message":"Any history available?\nCheck PLT_RESET_L and all SPI Bus Series Termination resistors.\nYou can also try to flash new BIOS."
    },
    {
        "post_id":61279,
        "thread_id":59521,
        "title":"820-4924-A .520A not turning on",
        "user_id":24760,
        "username":"2click",
        "post_date":"2020-06-22 00:12:07",
        "message":"Any history available? Left it on and the next morning won\u00b4t turn on...\nCheck PLT_RESET_L = 3.3v\nSPI Bus Series Termination resistors = all with the correct values...\nWhere can I find the BIOS? Can you send me a Link for that?\nThank you!"
    },
    {
        "post_id":61282,
        "thread_id":59521,
        "title":"820-4924-A .520A not turning on",
        "user_id":682,
        "username":"2informaticos",
        "post_date":"2020-06-22 01:44:33",
        "message":"Link should be already posted in other thread...\n[URL unfurl=\"true\"]https:\/\/drive.google.com\/file\/d\/1Hhdhd_t-9FxALozsa2067WnfRAUZqxNr\/view?usp=sharing[\/URL]"
    },
    {
        "post_id":61284,
        "thread_id":59521,
        "title":"820-4924-A .520A not turning on",
        "user_id":24760,
        "username":"2click",
        "post_date":"2020-06-22 03:16:34",
        "message":"And if that doesn\u00b4t work? What should I do?? Any sugestion?"
    },
    {
        "post_id":61287,
        "thread_id":59521,
        "title":"820-4924-A .520A not turning on",
        "user_id":682,
        "username":"2informaticos",
        "post_date":"2020-06-22 06:15:59",
        "message":"Maybe bad CPU.\nTry BIOS first..."
    },
    {
        "post_id":61304,
        "thread_id":59521,
        "title":"820-4924-A .520A not turning on",
        "user_id":24760,
        "username":"2click",
        "post_date":"2020-06-22 13:12:13",
        "message":"I tried the BIOS, it didn\u00b4t worked... I refuse to think its a dead cpu, it was one the night  before and working just fine... there must be something we\u00b4re missing...."
    },
    {
        "post_id":61308,
        "thread_id":59521,
        "title":"820-4924-A .520A not turning on",
        "user_id":682,
        "username":"2informaticos",
        "post_date":"2020-06-22 14:41:48",
        "message":"Could be, this is not an exact science...\n\nDid you get any activity on the SPI chip with o-scope?"
    }
]