[
    {
        "post_id":67271,
        "thread_id":60251,
        "title":"820-01041 Mac 2018 Restart at loading",
        "user_id":27270,
        "username":"Sam7771",
        "post_date":"2020-10-29 15:00:38",
        "message":"Hi,\n\nI am working with above Touch Bar  macbook and when turn on, Apple logo appearing and progress bar goes for about 10-15 seconds, then screen goes off and fan works very fast. CPU is getting very hot too. Where should I check?\nAfter few seconds again apple logo appear and goes it as a cycle."
    },
    {
        "post_id":67274,
        "thread_id":60251,
        "title":"820-01041 Mac 2018 Restart at loading",
        "user_id":682,
        "username":"2informaticos",
        "post_date":"2020-10-29 15:24:17",
        "message":"Start with DFU revive\/restore.\n\nAny history available?"
    },
    {
        "post_id":67279,
        "thread_id":60251,
        "title":"820-01041 Mac 2018 Restart at loading",
        "user_id":27270,
        "username":"Sam7771",
        "post_date":"2020-10-29 15:33:15",
        "message":"I didn't try DFU revive\/restore since customer needs data badly. Any way to recover data first? Don't see any lifeboat port in this model.\n\nNo water damage or any other burn marks etc.\n\nAlso forget to mention that CPU is very fast when turning on."
    },
    {
        "post_id":67290,
        "thread_id":60251,
        "title":"820-01041 Mac 2018 Restart at loading",
        "user_id":1057,
        "username":"piernov",
        "post_date":"2020-10-30 01:18:48",
        "message":"Try Target Disk Mode to backup the data."
    },
    {
        "post_id":67293,
        "thread_id":60251,
        "title":"820-01041 Mac 2018 Restart at loading",
        "user_id":682,
        "username":"2informaticos",
        "post_date":"2020-10-30 03:44:40",
        "message":"Revive option in DFU does NOT delete any data.\nRestore wipes internal SSD."
    }
]