[
    {
        "post_id":61724,
        "thread_id":59592,
        "title":"820-3787 wont pram reset after changing to pre-programmed u6100 firmware chip",
        "user_id":26621,
        "username":"grmacs",
        "post_date":"2020-07-01 11:03:28",
        "message":"I don't have way to reload bios so purchased a pre-loaded for this 820-3787. I've done these before no issues. I checked to make sure pin 1 is positioned and pins are good solder. I can do SMC reset as light changes on charger but PRAM reset does initial fan spin but never shuts down and restarts... Can I assume the U6100 is no bueno? Anything else to check? I've tried with external keyboard also."
    },
    {
        "post_id":61732,
        "thread_id":59592,
        "title":"820-3787 wont pram reset after changing to pre-programmed u6100 firmware chip",
        "user_id":682,
        "username":"2informaticos",
        "post_date":"2020-07-01 11:55:31",
        "message":"Apart of PRAM reset issue, the machine works good?"
    },
    {
        "post_id":61733,
        "thread_id":59592,
        "title":"820-3787 wont pram reset after changing to pre-programmed u6100 firmware chip",
        "user_id":26621,
        "username":"grmacs",
        "post_date":"2020-07-01 12:01:29",
        "message":"I dont get any display with the new pram. Fan spin charger light changes normally, and acted correctly for SMC reset. I tried holding down power button while pluggin in charger to see if anything different would happen but now display\/backlight nada. Just fan spin... no chime."
    },
    {
        "post_id":61741,
        "thread_id":59592,
        "title":"820-3787 wont pram reset after changing to pre-programmed u6100 firmware chip",
        "user_id":682,
        "username":"2informaticos",
        "post_date":"2020-07-01 13:19:45",
        "message":"Looks like board is not working at all, just turning on.\nWhy do you complain about chime then?\n\nDo you consider is good option to buy written BIOS chips, instead of doing them yourself???\nAn USB programmer can be aquired for less than 5 bucks.\nMedusa programmer is not cheap, but can do many things and save a lot of time.\nAnd \"time is (guess what)\"..."
    },
    {
        "post_id":61792,
        "thread_id":59592,
        "title":"820-3787 wont pram reset after changing to pre-programmed u6100 firmware chip",
        "user_id":26621,
        "username":"grmacs",
        "post_date":"2020-07-02 16:52:05",
        "message":"I have considered it but haven't hardly even had time to look into what to buy or how to do it... one of those things where I know it will be cheaper and faster in the end but trying to keep my head above water. Kind of like needing to spend time training somebody is a better move long term but sucks short term... I need to train ME on how to do it. :) I will get to it at some point for sure."
    },
    {
        "post_id":61813,
        "thread_id":59592,
        "title":"820-3787 wont pram reset after changing to pre-programmed u6100 firmware chip",
        "user_id":26621,
        "username":"grmacs",
        "post_date":"2020-07-03 03:29:04",
        "message":"[QUOTE=\"2informaticos, post: 61741, member: 682\"]\nLooks like board is not working at all, just turning on.\nWhy do you complain about chime then?\n\nDo you consider is good option to buy written BIOS chips, instead of doing them yourself???\nAn USB programmer can be aquired for less than 5 bucks.\nMedusa programmer is not cheap, but can do many things and save a lot of time.\nAnd \"time is (guess what)\"...\n[\/QUOTE]\nDo you have a recommendation for a usb programmer that I can simply download\/buy firmware and push to the chip after it's removed from the board? I found some that plug to the j-connectors and some that work with chip off the board but wondering what's most cost effective product that I can simply use to write new bios?"
    },
    {
        "post_id":61814,
        "thread_id":59592,
        "title":"820-3787 wont pram reset after changing to pre-programmed u6100 firmware chip",
        "user_id":682,
        "username":"2informaticos",
        "post_date":"2020-07-03 04:14:35",
        "message":"CH341 should be the cheapest.\nEZP2019+ is better.\nThere are many programmers..."
    },
    {
        "post_id":61817,
        "thread_id":59592,
        "title":"820-3787 wont pram reset after changing to pre-programmed u6100 firmware chip",
        "user_id":26621,
        "username":"grmacs",
        "post_date":"2020-07-03 04:23:48",
        "message":"Yeah I\u2019ve noticed! Haha. I was hoping to find something easy but I can\u2019t justify a Medusa as i won\u2019t have the volume to justify that spend anytime soon. I\u2019ll check out the ezp 2019"
    }
]