[
    {
        "post_id":60596,
        "thread_id":59461,
        "title":"820-3476 U2800 U3900 and PCH heating up",
        "user_id":2508,
        "username":"No-Clean",
        "post_date":"2020-06-07 12:45:09",
        "message":"Board had small corrosion on a couple caps and keyboard connector, got all that cleaned and fixed, but still same behaivior.\n\nU2800 U3900 and PCH are heating up while the board tries to startup.\n\nsmc bypass doesn't seem to do anything\n\nBoard sits around 70-80ma \n\nppbus 12.6v \nsmc_reset_l 3.3v\nsmc_onoff_l 3.4v"
    },
    {
        "post_id":60599,
        "thread_id":59461,
        "title":"820-3476 U2800 U3900 and PCH heating up",
        "user_id":682,
        "username":"2informaticos",
        "post_date":"2020-06-07 14:14:09",
        "message":"If the board only tries to start, no way to heats the chips so fast.\nUnless it takes some time \"trying to start\".\nWhat about 3V3_S5\/SUS and RTC voltage?\nAny S3\/0 voltage tries to appear?"
    },
    {
        "post_id":60601,
        "thread_id":59461,
        "title":"820-3476 U2800 U3900 and PCH heating up",
        "user_id":2508,
        "username":"No-Clean",
        "post_date":"2020-06-07 18:34:20",
        "message":"It takes a few seconds for the chips to heat up.\n\npp3v3_s5 3.3v\npp3v3_sus 3.3v\nppvrtc_g3h 3.3v\nrtc_reset_l 3.3v\n\npp3v3_s3 3.3v\nPP1V05_S0_REG_R 1.05v"
    },
    {
        "post_id":60615,
        "thread_id":59461,
        "title":"820-3476 U2800 U3900 and PCH heating up",
        "user_id":682,
        "username":"2informaticos",
        "post_date":"2020-06-08 03:25:53",
        "message":"So you also get S0 voltages.\nPost all the volatges you have and specify if go off in time, or stable."
    },
    {
        "post_id":60715,
        "thread_id":59461,
        "title":"820-3476 U2800 U3900 and PCH heating up",
        "user_id":2508,
        "username":"No-Clean",
        "post_date":"2020-06-09 20:45:38",
        "message":"This board now has a new SMC and clean BIOS, with those 2 things the behavior is the exact same.\n\nAt 12 seconds they all go off then come back and stay steady after that with their respective voltage.\n\nBoard stays around ~0.065a steady after a few seconds.\n\nPP5V_S0\nPP3V3_S0\nPP5V_S0_FET\nPP3V3_S0_FET\nPP3V3_S0SW_SSD\nPP0V675_S0_DDRVTT\nPP1V05_SUS\nPP1V5_S0\nPP1V05_S0SW_PCH_HSIO\nPPVCC_S0_CPU"
    },
    {
        "post_id":60727,
        "thread_id":59461,
        "title":"820-3476 U2800 U3900 and PCH heating up",
        "user_id":682,
        "username":"2informaticos",
        "post_date":"2020-06-10 03:31:13",
        "message":"Did you try known good BIOS posted on the forum?\nPLT_RESET_L is high?"
    },
    {
        "post_id":60765,
        "thread_id":59461,
        "title":"820-3476 U2800 U3900 and PCH heating up",
        "user_id":2508,
        "username":"No-Clean",
        "post_date":"2020-06-10 10:43:50",
        "message":"I just tried the BIOS from here: [URL]https:\/\/boards.rossmanngroup.com\/threads\/a1502-efi-serial-number-issue.59145\/#post-59146[\/URL]\n\nPLT_RESET_L is 0v\n\nStill same behavior"
    },
    {
        "post_id":60767,
        "thread_id":59461,
        "title":"820-3476 U2800 U3900 and PCH heating up",
        "user_id":682,
        "username":"2informaticos",
        "post_date":"2020-06-10 10:48:02",
        "message":"If board stays on and VCORE present, check PM_SYS_PWROK, PM_PCH_SYS_PWROK and VCCST_PWRGD."
    },
    {
        "post_id":60801,
        "thread_id":59461,
        "title":"820-3476 U2800 U3900 and PCH heating up",
        "user_id":2508,
        "username":"No-Clean",
        "post_date":"2020-06-10 22:36:48",
        "message":"Could no find PM_SYS_PWROK but found PM_SYSRST_L is 3.3v\nPM_PCH_SYS_PWROK  is 3.4v\nVCCST_PWRGD  is 1v"
    },
    {
        "post_id":60811,
        "thread_id":59461,
        "title":"820-3476 U2800 U3900 and PCH heating up",
        "user_id":682,
        "username":"2informaticos",
        "post_date":"2020-06-11 01:59:13",
        "message":"\"Could no find PM_SYS_PWROK\"\nSorry, I meant PM_PCH_PWROK..."
    },
    {
        "post_id":60844,
        "thread_id":59461,
        "title":"820-3476 U2800 U3900 and PCH heating up",
        "user_id":2508,
        "username":"No-Clean",
        "post_date":"2020-06-11 09:25:20",
        "message":"M_PCH_PWROK  3.4v"
    },
    {
        "post_id":60861,
        "thread_id":59461,
        "title":"820-3476 U2800 U3900 and PCH heating up",
        "user_id":682,
        "username":"2informaticos",
        "post_date":"2020-06-11 11:05:39",
        "message":"Looks like PCH issue; heat it with quality flux.\nMay have luck and could be only crap accumulated underneath..."
    },
    {
        "post_id":60866,
        "thread_id":59461,
        "title":"820-3476 U2800 U3900 and PCH heating up",
        "user_id":2508,
        "username":"No-Clean",
        "post_date":"2020-06-11 11:21:33",
        "message":"OK so in this board the PCH is integrated on the CPU, should I use the zaomao for this? \n\nIf not just put good flux and heat with how air?"
    },
    {
        "post_id":60868,
        "thread_id":59461,
        "title":"820-3476 U2800 U3900 and PCH heating up",
        "user_id":682,
        "username":"2informaticos",
        "post_date":"2020-06-11 11:23:29",
        "message":"NO, you don't need to melt the balls.\n180-200 degrees is more than enough to burn eventual crap.\nUse only hot air station..."
    },
    {
        "post_id":60939,
        "thread_id":59461,
        "title":"820-3476 U2800 U3900 and PCH heating up",
        "user_id":2508,
        "username":"No-Clean",
        "post_date":"2020-06-12 15:52:47",
        "message":"No luck..."
    },
    {
        "post_id":60940,
        "thread_id":59461,
        "title":"820-3476 U2800 U3900 and PCH heating up",
        "user_id":2508,
        "username":"No-Clean",
        "post_date":"2020-06-12 15:53:30",
        "message":"Thanks a lot!"
    }
]