[
    {
        "post_id":48192,
        "thread_id":48192,
        "title":"820-2533-B Hd not detected?",
        "user_id":1501,
        "username":"Dewanbd",
        "post_date":"2019-04-05 13:42:11",
        "message":"Hi,\nUnit works with usb external HD. Tried good know hd cable and HD. Not booting unlimited spinning with good known HD.\nThe measurement of J4501 are as following:\nSMBUS_SMC_MGMT_SCL p7=3v\nPP5V_S0_HDD_FLT p9,11=5v\nPP1V5_S0_HDD_FLT, p8=5v\nPP5V_S0_HDD_FLT,p10,12=5v\n Any help please.Thanks."
    },
    {
        "post_id":48196,
        "thread_id":48192,
        "title":"820-2533-B Hd not detected?",
        "user_id":682,
        "username":"2informaticos",
        "post_date":"2019-04-05 18:28:31",
        "message":"\"PP1V5_S0_HDD_FLT, p8=5v\"\nAre you sure???\nIt comes from PP1V5_S0; is L4502 OK?\n\nCheck FL4501\/02 and C4510\/11\/15\/16.\nAlso check all traces from that area."
    },
    {
        "post_id":48391,
        "thread_id":48192,
        "title":"820-2533-B Hd not detected?",
        "user_id":1501,
        "username":"Dewanbd",
        "post_date":"2019-04-13 10:32:34",
        "message":"I found the cable was faulty. It works fine now. Thank."
    }
]