{"post_id":45553,"thread_id":45553,"title":"820-00165 no green light when battery plugged in","user_id":615,"username":"laptopcity","post_date":"2019-02-02 04:35:05","message":"820-00165 no green light when battery plugged in, when battery unplugged board works fine , will not work from the battery only , somehow i have 19v on R7006 even with D7005 removed which means somehow the charger voltage is going directly to the battery ??? , i cant see on the schematic where these two voltage lines may short together if D7005 is removed"}
{"post_id":45555,"thread_id":45553,"title":"820-00165 no green light when battery plugged in","user_id":682,"username":"2informaticos","post_date":"2019-02-02 09:46:40","message":"Change Q7130.\nIts high-side part is shorted...\n\nBe sure C7125 is good."}
{"post_id":45649,"thread_id":45553,"title":"820-00165 no green light when battery plugged in","user_id":615,"username":"laptopcity","post_date":"2019-02-04 12:17:21","message":"Thankyou Q7130 sorted it :-)"}
