{"post_id":14836,"thread_id":14836,"title":"820-2936 No vcore","user_id":316,"username":"G.Beard","post_date":"2017-02-15 06:58:10","message":"Board badly liquid damaged from J9000 to Q5520.\n\nParts replaced, traces repaired.\n5V S0 = 5V\n3V3 S0 = 3V3\n1V05 S0 = 1V05\n\nALL_SYS_PWRGD = missing\nR7967 (1) = 3V3 (2) = missing\n\n\nAny ideas please?"}
{"post_id":14846,"thread_id":14836,"title":"820-2936 No vcore","user_id":682,"username":"2informaticos","post_date":"2017-02-15 10:10:45","message":"Tell us which secondary coils don't get voltage; leave CPU coils for the moment, check the others.\nAny one shorted to ground?\nPost Q7950 voltages."}
{"post_id":14856,"thread_id":14836,"title":"820-2936 No vcore","user_id":316,"username":"G.Beard","post_date":"2017-02-15 11:17:54","message":"ALL_SYS_PWRGD now  = 1.69V\nStill no vcore\n\nNo shorts on any chokes\nExpected voltages on all other chokes but L7100, L7550, L7510, L7520 = 0V"}
{"post_id":14863,"thread_id":14836,"title":"820-2936 No vcore","user_id":316,"username":"G.Beard","post_date":"2017-02-15 13:05:47","message":"Can anyone tell me what CPUIMVP_TON voltage at pin 2 of U7400 should be please?... Currently 0.5V"}
{"post_id":14867,"thread_id":14836,"title":"820-2936 No vcore","user_id":682,"username":"2informaticos","post_date":"2017-02-15 16:08:38","message":"ALL_SYS_PWRGD still too low, should be 3V.\nStrange to have 0.5V at TON, as that is the correct voltage when CPU power supply works...\nGet correct ALL_SYS_PWRGD first."}
