[
    {
        "post_id":97751,
        "thread_id":63731,
        "title":"820-3455 no green light",
        "user_id":44757,
        "username":"VinceLx2",
        "post_date":"2023-03-20 04:48:07",
        "message":"Hi,\nThis I\/O board for Macbook Air is powering the board properly, but no green or orange light appears. Is there any schematic available for it? I cannot find one on internet. Or any clue what to look at?"
    },
    {
        "post_id":97752,
        "thread_id":63731,
        "title":"820-3455 no green light",
        "user_id":682,
        "username":"2informaticos",
        "post_date":"2023-03-20 05:21:15",
        "message":"If the sound is OK, then you have problem with SYS_ONEWIRE conectivity.\nI fixed same problem running wire directly between MLB and LIO board (U6900).\nIf no sound, then no continuity for 3V42_G3H; same fix possible.\nI did this when had corrosion problems.\n\nFirst of all, should check the SYS_ONEWIRE circuitry on the LIO board.\nNo schematic\/boardview available.\n820-3213 schematic is good enough to help you.\n[URL unfurl=\"true\"]https:\/\/drive.google.com\/file\/d\/19xKUD1JvI2KFKt1WUl-mEzuKGq6tfvKh\/view?usp=share_link[\/URL]"
    },
    {
        "post_id":97798,
        "thread_id":63731,
        "title":"820-3455 no green light",
        "user_id":44757,
        "username":"VinceLx2",
        "post_date":"2023-03-21 08:12:02",
        "message":"Thank you for the schematic.\nSound is present, indeed a trace was broken on a test point for PP3V42_G3H_ONEWIRE\nNice repair! thanks"
    }
]