[
    {
        "post_id":54566,
        "thread_id":54566,
        "title":"Macbook Pro Retina 820-3332 Instant Death after powered USB plugged in. PLEASE HELP!",
        "user_id":19373,
        "username":"cryptopher",
        "post_date":"2019-11-18 12:09:17",
        "message":"820-3332 is now dead, I get no light on the charger. The board does not increase in temp. I got 20v coming in from my 85w adapter and g3h is active at 3.42v,,. I am fairly new to this so any info given in dummy format would be much appreciated. someone mentioned the USB power rail but I cant seem to pin point. \n\nThank you so much in advance."
    },
    {
        "post_id":54567,
        "thread_id":54566,
        "title":"Macbook Pro Retina 820-3332 Instant Death after powered USB plugged in. PLEASE HELP!",
        "user_id":682,
        "username":"2informaticos",
        "post_date":"2019-11-18 12:33:32",
        "message":"Post exact PPBUS_G3H voltage?\nDo you get 3V3_S5\/SUS?"
    },
    {
        "post_id":54568,
        "thread_id":54566,
        "title":"Macbook Pro Retina 820-3332 Instant Death after powered USB plugged in. PLEASE HELP!",
        "user_id":19373,
        "username":"cryptopher",
        "post_date":"2019-11-18 13:08:51",
        "message":"Now i am getting PPBUS_G3H .721v and dropping.. meaning it drops numbers by the second. on 3v3_S5 i got 0.001v"
    },
    {
        "post_id":54569,
        "thread_id":54566,
        "title":"Macbook Pro Retina 820-3332 Instant Death after powered USB plugged in. PLEASE HELP!",
        "user_id":682,
        "username":"2informaticos",
        "post_date":"2019-11-18 13:15:52",
        "message":"Post diode mode (red probe at ground) at L7030.\nAlso for L7220\/60 and the other coils.\nCheck for short (or low value) to ground on USB power and data lines."
    },
    {
        "post_id":54570,
        "thread_id":54566,
        "title":"Macbook Pro Retina 820-3332 Instant Death after powered USB plugged in. PLEASE HELP!",
        "user_id":19373,
        "username":"cryptopher",
        "post_date":"2019-11-18 13:22:27",
        "message":"can you guide me to the usb power lines???"
    },
    {
        "post_id":54571,
        "thread_id":54566,
        "title":"Macbook Pro Retina 820-3332 Instant Death after powered USB plugged in. PLEASE HELP!",
        "user_id":19373,
        "username":"cryptopher",
        "post_date":"2019-11-18 13:29:41",
        "message":"Diode mode: L7030 0.0424v \nL7220 gives me a beep at 0.018v\nL7060 0.129v"
    },
    {
        "post_id":54572,
        "thread_id":54566,
        "title":"Macbook Pro Retina 820-3332 Instant Death after powered USB plugged in. PLEASE HELP!",
        "user_id":19373,
        "username":"cryptopher",
        "post_date":"2019-11-18 13:52:09",
        "message":"I am also not getting anything on PP5V_S0"
    },
    {
        "post_id":54573,
        "thread_id":54566,
        "title":"Macbook Pro Retina 820-3332 Instant Death after powered USB plugged in. PLEASE HELP!",
        "user_id":682,
        "username":"2informaticos",
        "post_date":"2019-11-18 16:18:05",
        "message":"\"L7030 0.0424v\"\nAre you sure it is not close to 0.400-0.450 instead???\n\n\"L7220 gives me a beep at 0.018v\"\nThat is too low.\nI hope you've disconnected power when measured diode mode.\nAlso allow 10-15s after power is removed.\n\n\"usb power lines???\"\nPost diode mode at pins 2\/6 of U4600."
    },
    {
        "post_id":54583,
        "thread_id":54566,
        "title":"Macbook Pro Retina 820-3332 Instant Death after powered USB plugged in. PLEASE HELP!",
        "user_id":19373,
        "username":"cryptopher",
        "post_date":"2019-11-19 09:57:07",
        "message":"L7030: 0.436\nL7220: 0.018 (beeping) \n\nu4600\npin 2: 0.018 (beeping) \npin 6: 0.509"
    },
    {
        "post_id":54584,
        "thread_id":54566,
        "title":"Macbook Pro Retina 820-3332 Instant Death after powered USB plugged in. PLEASE HELP!",
        "user_id":19373,
        "username":"cryptopher",
        "post_date":"2019-11-19 09:59:56",
        "message":"Correct me if I am wrong, this means there is a short on pp5v_s4?"
    },
    {
        "post_id":54585,
        "thread_id":54566,
        "title":"Macbook Pro Retina 820-3332 Instant Death after powered USB plugged in. PLEASE HELP!",
        "user_id":19373,
        "username":"cryptopher",
        "post_date":"2019-11-19 10:18:03",
        "message":"PP5V_S5: 0.040v \n\nDoesn?t S5 need to work in order for s4 to turn on?"
    },
    {
        "post_id":54586,
        "thread_id":54566,
        "title":"Macbook Pro Retina 820-3332 Instant Death after powered USB plugged in. PLEASE HELP!",
        "user_id":682,
        "username":"2informaticos",
        "post_date":"2019-11-19 10:40:40",
        "message":"5V_S5 looks bad too.\nFew things connected there.\nCheck again disconnecting trackpad.\nAlso check for short on 5V_SUS.\nWhen you get 5V_S5, go for 5V_S4.\n\nDon't forget, PPBUS_G3H is first required."
    },
    {
        "post_id":54592,
        "thread_id":54566,
        "title":"Macbook Pro Retina 820-3332 Instant Death after powered USB plugged in. PLEASE HELP!",
        "user_id":19373,
        "username":"cryptopher",
        "post_date":"2019-11-19 10:54:16",
        "message":"PPbus_g3h is: 12v isn?t this supposed to be 12.5? \ni have the board taken out with nothing connected to it."
    },
    {
        "post_id":54593,
        "thread_id":54566,
        "title":"Macbook Pro Retina 820-3332 Instant Death after powered USB plugged in. PLEASE HELP!",
        "user_id":682,
        "username":"2informaticos",
        "post_date":"2019-11-19 11:25:16",
        "message":"Do you really get 12.0V?\nWhat about 5V_S5?\nSMC_PM_G2_EN present?"
    },
    {
        "post_id":54594,
        "thread_id":54566,
        "title":"Macbook Pro Retina 820-3332 Instant Death after powered USB plugged in. PLEASE HELP!",
        "user_id":19373,
        "username":"cryptopher",
        "post_date":"2019-11-19 11:55:30",
        "message":"Yes , I checked at Q5300 pin 4... it?s 12v sometimes 12.1\n5v_s5 is now 0.116v \nsmc_pm_g2 is at .455v"
    },
    {
        "post_id":54595,
        "thread_id":54566,
        "title":"Macbook Pro Retina 820-3332 Instant Death after powered USB plugged in. PLEASE HELP!",
        "user_id":682,
        "username":"2informaticos",
        "post_date":"2019-11-19 12:36:33",
        "message":"Check if SMC_RESET_L is good.\nI hope you still get 3V42 at least."
    },
    {
        "post_id":54600,
        "thread_id":54566,
        "title":"Macbook Pro Retina 820-3332 Instant Death after powered USB plugged in. PLEASE HELP!",
        "user_id":19373,
        "username":"cryptopher",
        "post_date":"2019-11-19 13:19:28",
        "message":"Smc reset is 2.456v \n\nkeep in mind that my light indicator does not turn on as well"
    },
    {
        "post_id":54601,
        "thread_id":54566,
        "title":"Macbook Pro Retina 820-3332 Instant Death after powered USB plugged in. PLEASE HELP!",
        "user_id":19373,
        "username":"cryptopher",
        "post_date":"2019-11-19 13:20:44",
        "message":"Yes 3v42 is good"
    },
    {
        "post_id":54602,
        "thread_id":54566,
        "title":"Macbook Pro Retina 820-3332 Instant Death after powered USB plugged in. PLEASE HELP!",
        "user_id":682,
        "username":"2informaticos",
        "post_date":"2019-11-19 13:33:18",
        "message":"Post all U5010 voltages.\nRemove F7040\/41 and check L7030 voltage."
    },
    {
        "post_id":54604,
        "thread_id":54566,
        "title":"Macbook Pro Retina 820-3332 Instant Death after powered USB plugged in. PLEASE HELP!",
        "user_id":19373,
        "username":"cryptopher",
        "post_date":"2019-11-19 13:59:42",
        "message":"U5010\npin 1: 3.431v\npin 2: 0.000v\npin 3: 3.431v\npin 4: 2.776v\npin 5: 2.446v\npin 6: 2.421v\npin 7: 3.432v\npin 8: 3.344v\n\nL7030: diode mode 0.420v \nvoltage mode plugged in 12.12v"
    },
    {
        "post_id":54612,
        "thread_id":54566,
        "title":"Macbook Pro Retina 820-3332 Instant Death after powered USB plugged in. PLEASE HELP!",
        "user_id":682,
        "username":"2informaticos",
        "post_date":"2019-11-19 15:58:22",
        "message":"You have a problem with SMC_RESET_L; it should be steady 3.3V.\nRemove R7000 and check it again.\nIf still bad, remove (clean at least) J6100.\nBe sure R5028 is OK; remove it and test SMC_RESET_R_L,\nIg good, then change SMC."
    },
    {
        "post_id":54616,
        "thread_id":54566,
        "title":"Macbook Pro Retina 820-3332 Instant Death after powered USB plugged in. PLEASE HELP!",
        "user_id":19373,
        "username":"cryptopher",
        "post_date":"2019-11-19 17:18:12",
        "message":"I don?t have a J6000 or R5028"
    },
    {
        "post_id":54633,
        "thread_id":54566,
        "title":"Macbook Pro Retina 820-3332 Instant Death after powered USB plugged in. PLEASE HELP!",
        "user_id":682,
        "username":"2informaticos",
        "post_date":"2019-11-20 03:40:09",
        "message":"J5100, sorry.\nAre you sure only R5000 connected to pin 5 of U5010?\nCheck continuity from there to R7000.\nR5028 is 0 ohm resistor, so may not be placed, if trace is OK."
    },
    {
        "post_id":54660,
        "thread_id":54566,
        "title":"Macbook Pro Retina 820-3332 Instant Death after powered USB plugged in. PLEASE HELP!",
        "user_id":19373,
        "username":"cryptopher",
        "post_date":"2019-11-20 18:02:06",
        "message":"There is continuity between r7000 and the few components connected to it.. I am still getting 2.6v on smc reset L... where is that power coming from.. I have a feeling something else is preventing it"
    },
    {
        "post_id":54661,
        "thread_id":54566,
        "title":"Macbook Pro Retina 820-3332 Instant Death after powered USB plugged in. PLEASE HELP!",
        "user_id":19373,
        "username":"cryptopher",
        "post_date":"2019-11-20 18:40:51",
        "message":"I removed R5000 and R7000 and I get 1.4v on smc reset"
    },
    {
        "post_id":54663,
        "thread_id":54566,
        "title":"Macbook Pro Retina 820-3332 Instant Death after powered USB plugged in. PLEASE HELP!",
        "user_id":19373,
        "username":"cryptopher",
        "post_date":"2019-11-20 22:46:33",
        "message":"Replaced R5000 and U5010 and now I have 3.4 on smc reset on pin 5 and R5000 but when I probe R7000 I still only get 1.6"
    },
    {
        "post_id":54664,
        "thread_id":54566,
        "title":"Macbook Pro Retina 820-3332 Instant Death after powered USB plugged in. PLEASE HELP!",
        "user_id":682,
        "username":"2informaticos",
        "post_date":"2019-11-21 00:11:09",
        "message":"SMC_RESET_L is generated through R5000, from 3V42.\nAnd U5010 controls the delay time required by reset function.\n\n\"when I probe R7000 I still only get 1.6\"\nDo you mean SMC_RESET_L drops to 1.6V when solder R7000?\nChange U7000 then.\nWhich pin of R7000 has 1.6V?"
    },
    {
        "post_id":54669,
        "thread_id":54566,
        "title":"Macbook Pro Retina 820-3332 Instant Death after powered USB plugged in. PLEASE HELP!",
        "user_id":19373,
        "username":"cryptopher",
        "post_date":"2019-11-21 00:41:17",
        "message":"Ok so now I get 3.27 without smc on.. with smc on I get 2.8"
    },
    {
        "post_id":54670,
        "thread_id":54566,
        "title":"Macbook Pro Retina 820-3332 Instant Death after powered USB plugged in. PLEASE HELP!",
        "user_id":682,
        "username":"2informaticos",
        "post_date":"2019-11-21 00:56:05",
        "message":"Try other SMC then..."
    },
    {
        "post_id":54773,
        "thread_id":54566,
        "title":"Macbook Pro Retina 820-3332 Instant Death after powered USB plugged in. PLEASE HELP!",
        "user_id":19373,
        "username":"cryptopher",
        "post_date":"2019-11-23 15:59:04",
        "message":"Replaced SMC and I now have a green light and computer boots.. thank you for all your help and please mark as solved"
    },
    {
        "post_id":54774,
        "thread_id":54566,
        "title":"Macbook Pro Retina 820-3332 Instant Death after powered USB plugged in. PLEASE HELP!",
        "user_id":19373,
        "username":"cryptopher",
        "post_date":"2019-11-23 17:07:41",
        "message":"Never mind spoke too soon... computer keeps restarting.. I get log in screen sometimes but it goes half way and gets stuck"
    },
    {
        "post_id":54777,
        "thread_id":54566,
        "title":"Macbook Pro Retina 820-3332 Instant Death after powered USB plugged in. PLEASE HELP!",
        "user_id":682,
        "username":"2informaticos",
        "post_date":"2019-11-23 18:23:57",
        "message":"Try SMC bypass mode.\nReball the SMC, be sure to have good solders."
    }
]